noseprogress/__init__.py
noseprogress/noseprogress.py
noseprogress-0.7.dist-info/DESCRIPTION.rst
noseprogress-0.7.dist-info/METADATA
noseprogress-0.7.dist-info/RECORD
noseprogress-0.7.dist-info/WHEEL
noseprogress-0.7.dist-info/entry_points.txt
noseprogress-0.7.dist-info/metadata.json
noseprogress-0.7.dist-info/top_level.txt
